cast_unknown/__init__.py
cast_unknown/__version__.py
cast_unknown/binary.py
cast_unknown/binary.pyi
cast_unknown/datetime.py
cast_unknown/datetime.pyi
cast_unknown/error.py
cast_unknown/error.pyi
cast_unknown/instance.py
cast_unknown/instance.pyi
cast_unknown/iterable.py
cast_unknown/iterable.pyi
cast_unknown/list.py
cast_unknown/list.pyi
cast_unknown/not_none.py
cast_unknown/not_none.pyi
cast_unknown/one.py
cast_unknown/one.pyi
cast_unknown/py.typed
cast_unknown/text.py
cast_unknown/text.pyi
cast_unknown-0.1.7.dist-info/LICENSE
cast_unknown-0.1.7.dist-info/METADATA
cast_unknown-0.1.7.dist-info/WHEEL
cast_unknown-0.1.7.dist-info/top_level.txt
cast_unknown-0.1.7.dist-info/RECORD
