Metadata-Version: 2.1
Name: cast-unknown
Version: 0.1.7
Summary: Cast unknown value to desired type with typing support.
Home-page: https://github.com/NateScarlet/cast-unknown-python
Author: NateScarlet
Author-email: NateScarlet@Gmail.com
License: MIT
Platform: UNKNOWN
Classifier: Development Status :: 3 - Alpha
Classifier: Intended Audience :: Developers
Classifier: License :: OSI Approved :: MIT License
Classifier: Operating System :: OS Independent
Classifier: Programming Language :: Python
Classifier: Programming Language :: Python :: 2
Classifier: Programming Language :: Python :: 3
Classifier: Programming Language :: Python :: 2.7
Classifier: Programming Language :: Python :: 3.4
Classifier: Programming Language :: Python :: 3.5
Classifier: Programming Language :: Python :: 3.6
Classifier: Programming Language :: Python :: 3.7
Classifier: Programming Language :: Python :: 3.8
Classifier: Programming Language :: Python :: 3.9
Classifier: Topic :: Software Development :: Libraries
Classifier: Typing :: Typed
License-File: LICENSE
Requires-Dist: six (~=1.15)
Requires-Dist: python-dateutil (~=2.8)
